pli_tests/pli_test.sv
module pli_test(input logic clk,                       // system clock
                input logic rst_b,                     // chip reset
                input logic [15:0] data_in,            // input data bus

                output logic [15:0] data_out);         // output data bus

always_ff @ ( posedge clk or negedge rst_b )
begin
  if ( !rst_b )
  begin
     data_out <= 16'h0;
  end // if ( !rst_b )
  else
  begin
     data_out <= data_in;
  end // else: !if( !rst_b )
end

endmodule

pli_tests/top_pli_test.sv
module top_pli_test;

logic clk;                       // system clock
logic rst_b;                     // chip reset
logic [15:0] data_in;            // input data bus
logic [15:0] data_out;           // output data bus

logic [15:0] start_val;          // start value to use
logic [15:0] limit;              // how many tests to run
integer      count;              // loop counter

initial   // get command line args
begin
   if ( $value$plusargs("START_VALUE=%h",start_val) )
      $display("using provided start value %h",start_val);
   else
   begin
      start_val = 16'h0;
      $display("using default start value %h",start_val);
   end
   if ( $value$plusargs("RUN_LIMIT=%h",limit) )
      $display("using run limit of %h",limit);
   else
   begin
      limit = 10;
      $display("using default start value %h",start_val);
   end
end

initial   // create clock and reset
begin
   clk      <= 1'b0;
   rst_b    <= 1'b0;
   data_in  <= 16'h0;
   #1;
   data_in  <= start_val;
   #4 rst_b <= 1'b1;

   while ( 1 )
   begin
      #5 clk <= 1'b1;
      #5 clk <= 1'b0;
   end
end

initial      // the loop!
begin
  wait ( rst_b === 1'b1 );        // get out of reset
  wait ( clk == 1'b1 );           // wait for start value to be loaded
   
  for ( count = 0 ; count < limit ; count = count + 1 )
  begin
    wait ( clk == 1'b0 );
    $pli_test_next(data_out,data_in);
    wait ( clk == 1'b1 );
  end

  wait(clk == 1'b0);   // MUST LEAVE SO GRADING WORKS!
  wait(clk == 1'b1);
  wait(clk == 1'b0);
  $finish;
end

pli_test pli_test (.clk           ( clk            ),    // system clock
                   .rst_b         ( rst_b          ),    // chip reset
                   .data_in       ( data_in        ),    // data bus

                   .data_out      ( data_out       ) );  // output data bus

always @ ( * )
  $display("%t data_in %h data_out %h",$time(),data_in,data_out);

// initial
// begin
// $fsdbDumpfile("top_pli_test.fsdb");
// $fsdbDumpvars(0,pli_test);
// end

endmodule

pli_tests/top_pli_test (1).vcd
$date
	Fri Feb  6 18:27:08 2026
$end

$version
	Synopsys VCS version T-2022.06-SP2-1_Full64
$end

$timescale
	1ps
$end

$comment Csum: 1 2f2398a63bce18bc $end


$scope module top_pli_test $end

$scope module pli_test $end
$var reg 1 ! clk $end
$var reg 1 " rst_b $end
$var reg 16 # data_in [15:0] $end
$var reg 16 $ data_out [15:0] $end
$upscope $end

$upscope $end

$enddefinitions $end

#0
$dumpvars
b0000000000000000 #
b0000000000000000 $
0!
0"
$end
#5
1"
#10
1!
#15
0!
#20
1!
#25
0!
b0000000000000001 #
#30
1!
b0000000000000001 $
#35
0!
b0000000000000010 #
#40
1!
b0000000000000010 $
#45
0!
b0000000000000011 #
#50
1!
b0000000000000011 $
#55
0!
b0000000000000100 #
#60
1!
b0000000000000100 $
#65
0!
b0000000000000101 #
#70
1!
b0000000000000101 $
#75
0!
b0000000000000110 #
#80
1!
b0000000000000110 $
#85
0!
b0000000000000111 #
#90
1!
b0000000000000111 $
#95
0!
b0000000000001000 #
#100
1!
b0000000000001000 $
#105
0!
b0000000000001001 #
#110
1!
b0000000000001001 $
